numwordify/__init__.py
numwordify/converter.py
numwordify/config/__init__.py
numwordify/config/loader.py
numwordify/config/settings.py
numwordify/data/arabic.json
numwordify/data/english.json
numwordify-0.1.1.dist-info/licenses/LICENSE
numwordify-0.1.1.dist-info/METADATA
numwordify-0.1.1.dist-info/WHEEL
numwordify-0.1.1.dist-info/top_level.txt
numwordify-0.1.1.dist-info/zip-safe
numwordify-0.1.1.dist-info/RECORD
