Metadata-Version: 2.4
Name: numwordify
Version: 0.1.1
Summary: A lightweight, performant number-to-words converter supporting English and Arabic
Home-page: https://github.com/mabukhashabeh/numwordify
Author: Mohammad Abu Khahsabeh
Author-email: Mohammad Abu Khahsabeh <abukhashabehmohammad@gmail.com>
License: MIT
Project-URL: Homepage, https://github.com/mabukhashabeh/numwordify
Project-URL: Documentation, https://github.com/mabukhashabeh/numwordify#readme
Project-URL: Repository, https://github.com/mabukhashabeh/numwordify
Project-URL: Issues, https://github.com/mabukhashabeh/numwordify/issues
Keywords: number,words,converter,english,arabic,numwordify,text
Classifier: Development Status :: 4 - Beta
Classifier: Intended Audience :: Developers
Classifier: License :: OSI Approved :: MIT License
Classifier: Programming Language :: Python :: 3
Classifier: Programming Language :: Python :: 3.8
Classifier: Programming Language :: Python :: 3.9
Classifier: Programming Language :: Python :: 3.10
Classifier: Programming Language :: Python :: 3.11
Classifier: Programming Language :: Python :: 3.12
Classifier: Topic :: Software Development :: Libraries :: Python Modules
Classifier: Topic :: Text Processing :: Linguistic
Requires-Python: >=3.8
License-File: LICENSE
Dynamic: author
Dynamic: home-page
Dynamic: license-file
Dynamic: requires-python
